c3a3_config_loader-2.0.0.dist-info/licenses/LICENSE.md
config_loader/__init__.py
config_loader/builder.py
config_loader/callable_validators.py
config_loader/command_parser.py
config_loader/command_validator.py
config_loader/config_schema.json
config_loader/deprecation.py
config_loader/encryption.py
config_loader/error_recovery.py
config_loader/exclusion_validator.py
config_loader/loaders.py
config_loader/main.py
config_loader/models.py
config_loader/plugin_interface.py
config_loader/plugin_manager.py
config_loader/result.py
config_loader/serialization.py
config_loader/tokenizer.py
config_loader/validator.py
config_loader/value_provider.py
c3a3_config_loader-2.0.0.dist-info/METADATA
c3a3_config_loader-2.0.0.dist-info/WHEEL
c3a3_config_loader-2.0.0.dist-info/top_level.txt
c3a3_config_loader-2.0.0.dist-info/RECORD
