Metadata-Version: 2.4
Name: c3a3-config_loader
Version: 2.0.0
Summary: Loads configurations from different files with ease
Author-email: ã <me@c3a3.me>
Project-URL: Homepage, https://github.com/mrtu/c3a3-config_loader
Project-URL: Documentation, https://github.com/mrtu/c3a3-config_loader#readme
Project-URL: Issues, https://github.com/mrtu/c3a3-config_loader/issues
Project-URL: Bug Tracker, https://github.com/mrtu/c3a3-config_loader/issues
Project-URL: License, https://github.com/mrtu/c3a3-config_loader/blob/main/LICENSE
Classifier: Programming Language :: Python :: 3
Classifier: Programming Language :: Python :: 3.11
Classifier: Intended Audience :: Developers
Classifier: Topic :: Software Development :: Libraries
Classifier: License :: Other/Proprietary License
Requires-Python: >=3.11
License-File: LICENSE.md
Requires-Dist: cryptography>=42.0.0
Requires-Dist: pyyaml>=6.0.0
Provides-Extra: dev
Requires-Dist: pytest>=8; extra == "dev"
Requires-Dist: pytest-cov; extra == "dev"
Requires-Dist: mypy; extra == "dev"
Requires-Dist: ruff; extra == "dev"
Dynamic: license-file
